adminpanel/__init__.py
adminpanel/admin.py
adminpanel/apps.py
adminpanel/configuration.py
adminpanel/models.py
adminpanel/setup.py
adminpanel/tests.py
adminpanel/urls.py
adminpanel/model/__init__.py
adminpanel/model/emails.py
adminpanel/model/media.py
adminpanel/model/menus.py
adminpanel/model/options.py
adminpanel/model/package.py
adminpanel/model/pagemeta.py
adminpanel/model/pages.py
adminpanel/model/properties.py
adminpanel/model/services.py
adminpanel/model/testimonial.py
adminpanel/model/usermeta.py
adminpanel/static/adminpanel/css/AdminLTE.min.css
adminpanel/static/adminpanel/css/_all-skins.min.css
adminpanel/static/adminpanel/css/bootstrap.min.css
adminpanel/static/adminpanel/css/font-awesome.min.css
adminpanel/static/adminpanel/css/font-awesome1.min.css
adminpanel/static/adminpanel/css/ionicons.min.css
adminpanel/static/adminpanel/css/jquery-jvectormap.css
adminpanel/static/adminpanel/css/jquery-te-1.4.0.css
adminpanel/static/adminpanel/css/jquery-te.png
adminpanel/static/adminpanel/css/style.css
adminpanel/static/adminpanel/css/menu/bootstrap-iconpicker.css
adminpanel/static/adminpanel/css/menu/bootstrap-iconpicker.min.css
adminpanel/static/adminpanel/fonts/fontawesome-webfont3e6e.eot
adminpanel/static/adminpanel/fonts/fontawesome-webfont3e6e.svg
adminpanel/static/adminpanel/fonts/fontawesome-webfont3e6e.ttf
adminpanel/static/adminpanel/fonts/fontawesome-webfont3e6e.woff
adminpanel/static/adminpanel/fonts/fontawesome-webfont3e6e.woff2
adminpanel/static/adminpanel/fonts/fontawesome-webfontd41d.eot
adminpanel/static/adminpanel/fonts/glyphicons-halflings-regular.eot
adminpanel/static/adminpanel/fonts/glyphicons-halflings-regular.svg
adminpanel/static/adminpanel/fonts/glyphicons-halflings-regular.ttf
adminpanel/static/adminpanel/fonts/glyphicons-halflings-regular.woff
adminpanel/static/adminpanel/fonts/glyphicons-halflings-regular.woff2
adminpanel/static/adminpanel/fonts/glyphicons-halflings-regulard41d.eot
adminpanel/static/adminpanel/fonts/ionicons28b5.eot
django_adminpanel-1.1.0.dist-info/LICENSE
django_adminpanel-1.1.0.dist-info/METADATA
django_adminpanel-1.1.0.dist-info/WHEEL
django_adminpanel-1.1.0.dist-info/top_level.txt
django_adminpanel-1.1.0.dist-info/RECORD
