Metadata-Version: 2.1
Name: django-adminpanel
Version: 1.1.0
Summary: Admin panel for django
Home-page: https://github.com/pythoncommunities/adminpanel
Author: Dev
Author-email: python.communities@gmail.com
License: UNKNOWN
Platform: UNKNOWN
Classifier: Programming Language :: Python :: 3
Classifier: License :: Freeware
Classifier: Operating System :: OS Independent
